{
  "http://json-schema.org/draft-04/schema#": "SchemaDocument",
  "http://json-schema.org/draft-04/schema#/definitions/schemaArray": "SchemaArray",
  "http://json-schema.org/draft-04/schema#/definitions/positiveInteger": "PositiveInteger",
  "http://json-schema.org/draft-04/schema#/definitions/positiveIntegerDefault0": "PositiveIntegerDefault0",
  "http://json-schema.org/draft-04/schema#/definitions/simpleTypes": "SimpleTypes",
  "http://json-schema.org/draft-04/schema#/definitions/stringArray": "StringArray",
  "http://json-schema.org/draft-04/schema#/properties/id": "Id",
  "http://json-schema.org/draft-04/schema#/properties/$schema": "Schema",
  "http://json-schema.org/draft-04/schema#/properties/title": "Title",
  "http://json-schema.org/draft-04/schema#/properties/description": "Description",
  "http://json-schema.org/draft-04/schema#/properties/default": "Default",
  "http://json-schema.org/draft-04/schema#/properties/multipleOf": "MultipleOf",
  "http://json-schema.org/draft-04/schema#/properties/maximum": "Maximum",
  "http://json-schema.org/draft-04/schema#/properties/exclusiveMaximum": "ExclusiveMaximum",
  "http://json-schema.org/draft-04/schema#/properties/minimum": "Minimum",
  "http://json-schema.org/draft-04/schema#/properties/exclusiveMinimum": "ExclusiveMinimum",
  "http://json-schema.org/draft-04/schema#/properties/maxLength": "MaxLength",
  "http://json-schema.org/draft-04/schema#/properties/minLength": "MinLength",
  "http://json-schema.org/draft-04/schema#/properties/pattern": "Pattern",
  "http://json-schema.org/draft-04/schema#/properties/additionalItems": "AdditionalItems",
  "http://json-schema.org/draft-04/schema#/properties/items": "PropertiesItems",
  "http://json-schema.org/draft-04/schema#/properties/maxItems": "MaxItems",
  "http://json-schema.org/draft-04/schema#/properties/minItems": "MinItems",
  "http://json-schema.org/draft-04/schema#/properties/uniqueItems": "UniqueItems",
  "http://json-schema.org/draft-04/schema#/properties/maxProperties": "MaxProperties",
  "http://json-schema.org/draft-04/schema#/properties/minProperties": "MinProperties",
  "http://json-schema.org/draft-04/schema#/properties/required": "Required",
  "http://json-schema.org/draft-04/schema#/properties/additionalProperties": "PropertiesAdditionalProperties",
  "http://json-schema.org/draft-04/schema#/properties/definitions": "Definitions",
  "http://json-schema.org/draft-04/schema#/properties/properties": "Properties",
  "http://json-schema.org/draft-04/schema#/properties/patternProperties": "PatternProperties",
  "http://json-schema.org/draft-04/schema#/properties/dependencies": "Dependencies",
  "http://json-schema.org/draft-04/schema#/properties/enum": "Enum",
  "http://json-schema.org/draft-04/schema#/properties/type": "Type",
  "http://json-schema.org/draft-04/schema#/properties/format": "Format",
  "http://json-schema.org/draft-04/schema#/properties/allOf": "AllOf",
  "http://json-schema.org/draft-04/schema#/properties/anyOf": "AnyOf",
  "http://json-schema.org/draft-04/schema#/properties/oneOf": "OneOf",
  "http://json-schema.org/draft-04/schema#/properties/not": "Not",
  "http://json-schema.org/draft-04/schema#/definitions/schemaArray/items": "SchemaArrayItems",
  "http://json-schema.org/draft-04/schema#/definitions/positiveIntegerDefault0/allOf/0": "PositiveIntegerDefault00",
  "http://json-schema.org/draft-04/schema#/definitions/positiveIntegerDefault0/allOf/1": "PositiveIntegerDefault01",
  "http://json-schema.org/draft-04/schema#/definitions/stringArray/items": "StringArrayItems",
  "http://json-schema.org/draft-04/schema#/properties/additionalItems/anyOf/0": "AdditionalItems0",
  "http://json-schema.org/draft-04/schema#/properties/additionalItems/anyOf/1": "AdditionalItems1",
  "http://json-schema.org/draft-04/schema#/properties/items/anyOf/0": "Items0",
  "http://json-schema.org/draft-04/schema#/properties/items/anyOf/1": "Items1",
  "http://json-schema.org/draft-04/schema#/properties/additionalProperties/anyOf/0": "AdditionalProperties0",
  "http://json-schema.org/draft-04/schema#/properties/additionalProperties/anyOf/1": "AdditionalProperties1",
  "http://json-schema.org/draft-04/schema#/properties/definitions/additionalProperties": "DefinitionsAdditionalProperties",
  "http://json-schema.org/draft-04/schema#/properties/properties/additionalProperties": "PropertiesPropertiesAdditionalProperties",
  "http://json-schema.org/draft-04/schema#/properties/patternProperties/additionalProperties": "PatternPropertiesAdditionalProperties",
  "http://json-schema.org/draft-04/schema#/properties/dependencies/additionalProperties": "DependenciesAdditionalProperties",
  "http://json-schema.org/draft-04/schema#/properties/type/anyOf/0": "Type0",
  "http://json-schema.org/draft-04/schema#/properties/type/anyOf/1": "Type1",
  "http://json-schema.org/draft-04/schema#/properties/dependencies/additionalProperties/anyOf/0": "Dependencies0",
  "http://json-schema.org/draft-04/schema#/properties/dependencies/additionalProperties/anyOf/1": "Dependencies1",
  "http://json-schema.org/draft-04/schema#/properties/type/anyOf/1/items": "TypeItems"
}